iotdb/Session.py
iotdb/SessionPool.py
iotdb/__init__.py
iotdb/table_session.py
iotdb/table_session_pool.py
iotdb/dbapi/Connection.py
iotdb/dbapi/Cursor.py
iotdb/dbapi/Exceptions.py
iotdb/dbapi/__init__.py
iotdb/sqlalchemy/IoTDBDialect.py
iotdb/sqlalchemy/IoTDBIdentifierPreparer.py
iotdb/sqlalchemy/IoTDBSQLCompiler.py
iotdb/sqlalchemy/IoTDBTypeCompiler.py
iotdb/sqlalchemy/__init__.py
iotdb/template/MeasurementNode.py
iotdb/template/Template.py
iotdb/template/TemplateNode.py
iotdb/template/TemplateQueryType.py
iotdb/template/__init__.py
iotdb/thrift/__init__.py
iotdb/thrift/ainode/IAINodeRPCService.py
iotdb/thrift/ainode/__init__.py
iotdb/thrift/ainode/constants.py
iotdb/thrift/ainode/ttypes.py
iotdb/thrift/common/__init__.py
iotdb/thrift/common/constants.py
iotdb/thrift/common/ttypes.py
iotdb/thrift/confignode/IConfigNodeRPCService.py
iotdb/thrift/confignode/__init__.py
iotdb/thrift/confignode/constants.py
iotdb/thrift/confignode/ttypes.py
iotdb/thrift/datanode/IDataNodeRPCService.py
iotdb/thrift/datanode/MPPDataExchangeService.py
iotdb/thrift/datanode/__init__.py
iotdb/thrift/datanode/constants.py
iotdb/thrift/datanode/ttypes.py
iotdb/thrift/rpc/IClientRPCService.py
iotdb/thrift/rpc/__init__.py
iotdb/thrift/rpc/constants.py
iotdb/thrift/rpc/ttypes.py
iotdb/tsfile/__init__.py
iotdb/tsfile/common/__init__.py
iotdb/tsfile/common/constant/__init__.py
iotdb/tsfile/common/constant/tsfile_constant.py
iotdb/tsfile/utils/__init__.py
iotdb/tsfile/utils/date_utils.py
iotdb/tsfile/utils/pair.py
iotdb/tsfile/utils/read_write_io_utils.py
iotdb/tsfile/utils/tsblock_serde.py
iotdb/utils/BitMap.py
iotdb/utils/Field.py
iotdb/utils/IoTDBConstants.py
iotdb/utils/NumpyTablet.py
iotdb/utils/RowRecord.py
iotdb/utils/SessionDataSet.py
iotdb/utils/Tablet.py
iotdb/utils/__init__.py
iotdb/utils/exception.py
iotdb/utils/iotdb_rpc_dataset.py
iotdb/utils/rpc_utils.py
tests/__init__.py
tests/integration/__init__.py
tests/integration/iotdb_container.py
apache_iotdb-2.0.6.dist-info/METADATA
apache_iotdb-2.0.6.dist-info/WHEEL
apache_iotdb-2.0.6.dist-info/entry_points.txt
apache_iotdb-2.0.6.dist-info/top_level.txt
apache_iotdb-2.0.6.dist-info/RECORD
