Metadata-Version: 2.4
Name: apache-iotdb
Version: 2.0.6
Summary: Apache IoTDB client API
Author-email: Apache IoTDB <dev@iotdb.apache.org>
License-Expression: Apache-2.0
Project-URL: Homepage, https://iotdb.apache.org
Project-URL: Documentation, https://github.com/apache/iotdb
Keywords: iotdb,apache,client,API
Classifier: Programming Language :: Python :: 3
Classifier: Operating System :: OS Independent
Classifier: Topic :: Software Development :: Libraries
Classifier: Topic :: Software Development :: Libraries :: Python Modules
Requires-Python: >=3.6
Requires-Dist: thrift>=0.14.1
Requires-Dist: pandas>=1.0.0
Requires-Dist: numpy>=1.0.0
Requires-Dist: sqlalchemy>=1.4
Requires-Dist: sqlalchemy-utils>=0.37.8
Requires-Dist: tzlocal>=4.0
